aezpz/__about__.py
aezpz/__init__.py
aezpz/api.py
aezpz/datasets.py
aezpz/globals.json
aezpz/schema.py
aezpz-0.0.4.dist-info/METADATA
aezpz-0.0.4.dist-info/WHEEL
aezpz-0.0.4.dist-info/licenses/LICENSE
aezpz-0.0.4.dist-info/RECORD
